tair_pulse/__init__.py
tair_pulse/keys.py
tair_pulse/main.py
tair_pulse-1.3.4.dist-info/METADATA
tair_pulse-1.3.4.dist-info/WHEEL
tair_pulse-1.3.4.dist-info/entry_points.txt
tair_pulse-1.3.4.dist-info/RECORD
