Metadata-Version: 2.4
Name: tair-pulse
Version: 1.3.4
Summary: TairPulse is a tool to visualize the latency and availability of Tair/Redis instances.
Project-URL: Homepage, https://github.com/tair-opensource
Project-URL: Bug Tracker, https://github.com/tair-opensource
Author-email: Tair <tair-opensource@alibabacloud.com>, suxb201 <suxb201@gmail.com>
Classifier: License :: OSI Approved :: MIT License
Classifier: Operating System :: OS Independent
Classifier: Programming Language :: Python :: 3
Classifier: Topic :: Database
Requires-Python: >=3.6
Requires-Dist: plotly-resampler<1.0.0,>=0.10.0
Requires-Dist: plotly<6.0.0,>=5.0.0
Requires-Dist: redis<7.0.0,>=5.0.0
Requires-Dist: rich<14.0.0,>=13.0.0
